drymail.py
drymail-0.0.6.dist-info/LICENSE
drymail-0.0.6.dist-info/METADATA
drymail-0.0.6.dist-info/WHEEL
drymail-0.0.6.dist-info/top_level.txt
drymail-0.0.6.dist-info/RECORD
