Metadata-Version: 2.1
Name: drymail
Version: 0.0.6
Summary: Drymail is a minimalist wrapper over Python’s existing smtplib and email libraries, designed to be friendly but unrestrictive. 
Home-page: https://github.com/SkullTech/drymail
Author: Sumit Ghosh
Author-email: sumit@sumit-ghosh.com
License: MIT
Keywords: smtp email
Platform: UNKNOWN
Classifier: Development Status :: 3 - Alpha
Classifier: Intended Audience :: Developers
Classifier: Topic :: Software Development :: Libraries :: Python Modules
Classifier: License :: OSI Approved :: MIT License
Classifier: Programming Language :: Python :: 3
Classifier: Programming Language :: Python :: 3.5
Classifier: Programming Language :: Python :: 3.6
Classifier: Programming Language :: Python :: 3.7
